dynamic_dns_update_client/__init__.py
dynamic_dns_update_client/cache.py
dynamic_dns_update_client/constants.py
dynamic_dns_update_client/dyn_dns_update.py
dynamic_dns_update_client/ip_address.py
dynamic_dns_update_client/types.py
dynamic_dns_update_client/utils.py
dynamic_dns_update_client-1.0.0.dist-info/LICENSE
dynamic_dns_update_client-1.0.0.dist-info/METADATA
dynamic_dns_update_client-1.0.0.dist-info/WHEEL
dynamic_dns_update_client-1.0.0.dist-info/entry_points.txt
dynamic_dns_update_client-1.0.0.dist-info/RECORD
