Metadata-Version: 2.3
Name: dynamic-dns-update-client
Version: 1.0.0
Summary: A CLI tool for obtaining and updating your public IP address at dynamic DNS providers.
License: MIT
Author: Max Pfeiffer
Author-email: max@maxpfeiffer.ch
Requires-Python: >=3.11
Classifier: License :: OSI Approved :: MIT License
Classifier: Programming Language :: Python :: 3
Classifier: Programming Language :: Python :: 3.11
Classifier: Programming Language :: Python :: 3.12
Classifier: Programming Language :: Python :: 3.13
Requires-Dist: click (>=8.1.7,<9.0.0)
Requires-Dist: ifcfg (>=0.24,<0.25)
Requires-Dist: requests (>=2.30.0,<3.0.0)
Project-URL: Homepage, https://github.com/max-pfeiffer/dynamic-dns-update-client
